cpufeature/__init__.py
cpufeature/bitmask.py
cpufeature/extension.cp310-win32.pyd
cpufeature/test_cpufeature.py
cpufeature/version.py
cpufeature-0.2.1.dist-info/LICENSE
cpufeature-0.2.1.dist-info/METADATA
cpufeature-0.2.1.dist-info/WHEEL
cpufeature-0.2.1.dist-info/top_level.txt
cpufeature-0.2.1.dist-info/RECORD
