Metadata-Version: 2.1
Name: cpufeature
Version: 0.2.1
Summary: Python CPU Feature Detection
Home-page: http://github.com/robbmcleod/cpufeature
Author: Robert A. McLeod
Author-email: robbmcleod@gmail.com
Maintainer: Robert A. McLeod
Maintainer-email: robbmcleod@gmail.com
License: https://creativecommons.org/publicdomain/zero/1.0/legalcode
Platform: any
Classifier: Development Status :: 3 - Alpha
Classifier: Intended Audience :: Developers
Classifier: Intended Audience :: Information Technology
Classifier: License :: CC0 1.0 Universal (CC0 1.0) Public Domain Dedication
Classifier: Programming Language :: Python
Classifier: Programming Language :: Python :: 3.8
Classifier: Programming Language :: Python :: 3.9
Classifier: Programming Language :: Python :: 3.10
Classifier: Programming Language :: Python :: 3.11
Classifier: Topic :: Software Development :: Libraries :: Python Modules
Classifier: Topic :: System :: Hardware
Classifier: Operating System :: Microsoft :: Windows
Classifier: Operating System :: Unix
License-File: LICENSE
